[
  {
    "_id": {
      "$oid": "698bb2e0b7b16f887d682de5"
    },
    "title": "The Sovereign Suites",
    "description": "Ultra-luxury sky villas with private pools and landscaped terraces.",
    "price": "₹12.5 Cr onwards",
    "location": "Golf Course Road, Gurugram",
    "images": [
      "/assets/properties/property_0_0.jpg"
    ],
    "type": "Residential",
    "status": "Available",
    "amenities": [
      "Private Pool",
      "Gym",
      "Concierge",
      "Sky Lounge"
    ],
    "details": {
      "bedrooms": 4,
      "bathrooms": 5,
      "area": "5500 sqft"
    },
    "featured": true,
    "__v": 0,
    "createdAt": {
      "$date": "2026-02-10T22:36:16.177Z"
    },
    "updatedAt": {
      "$date": "2026-02-10T22:36:16.177Z"
    }
  },
  {
    "_id": {
      "$oid": "698bb2e0b7b16f887d682de6"
    },
    "title": "Empire Estate",
    "description": "A masterpiece of contemporary architecture in the heart of the business district.",
    "price": "₹8.9 Cr onwards",
    "location": "Central Business District, Gurugram",
    "images": [
      "/assets/properties/property_1_0.jpg"
    ],
    "type": "Residential",
    "status": "Available",
    "amenities": [
      "Infinity Pool",
      "Spa",
      "Yoga Studio",
      "Smart Home"
    ],
    "details": {
      "bedrooms": 3,
      "bathrooms": 4,
      "area": "3800 sqft"
    },
    "featured": true,
    "__v": 0,
    "createdAt": {
      "$date": "2026-02-10T22:36:16.180Z"
    },
    "updatedAt": {
      "$date": "2026-02-10T22:36:16.180Z"
    }
  },
  {
    "_id": {
      "$oid": "698bb2e0b7b16f887d682de7"
    },
    "title": "Azure Tower",
    "description": "Luxury apartments with 360-degree city views and premium finishes.",
    "price": "₹5.5 Cr onwards",
    "location": "Sector 54, Gurugram",
    "images": [
      "/assets/properties/property_2_0.jpg"
    ],
    "type": "Residential",
    "status": "Available",
    "amenities": [
      "Clubhouse",
      "Tennis Court",
      "Park"
    ],
    "details": {
      "bedrooms": 3,
      "bathrooms": 3,
      "area": "2800 sqft"
    },
    "featured": false,
    "__v": 0,
    "createdAt": {
      "$date": "2026-02-10T22:36:16.181Z"
    },
    "updatedAt": {
      "$date": "2026-02-10T22:36:16.181Z"
    }
  },
  {
    "_id": {
      "$oid": "698bb2e0b7b16f887d682de8"
    },
    "title": "Platinum Business Hub",
    "description": "Grade-A commercial office spaces with state-of-the-art infrastructure and premium amenities.",
    "price": "₹18,000/sqft onwards",
    "location": "Cyber City, Gurugram",
    "images": [
      "/assets/properties/property_3_0.jpg"
    ],
    "type": "Commercial",
    "status": "Available",
    "amenities": [
      "24/7 Security",
      "High-Speed Elevators",
      "Conference Rooms",
      "Cafeteria"
    ],
    "details": {
      "bedrooms": 0,
      "bathrooms": 2,
      "area": "5000 sqft"
    },
    "featured": true,
    "__v": 0,
    "createdAt": {
      "$date": "2026-02-12T09:30:00.000Z"
    },
    "updatedAt": {
      "$date": "2026-02-12T09:30:00.000Z"
    }
  },
  {
    "_id": {
      "$oid": "698bb2e0b7b16f887d682de9"
    },
    "title": "Signature Retail Plaza",
    "description": "Premium retail spaces in a high-footfall location with excellent visibility and accessibility.",
    "price": "₹25,000/sqft onwards",
    "location": "MG Road, Gurugram",
    "images": [
      "/assets/properties/property_4_0.jpg"
    ],
    "type": "Commercial",
    "status": "Upcoming",
    "amenities": [
      "Ample Parking",
      "Food Court",
      "Entertainment Zone",
      "Smart Building"
    ],
    "details": {
      "bedrooms": 0,
      "bathrooms": 3,
      "area": "8000 sqft"
    },
    "featured": false,
    "__v": 0,
    "createdAt": {
      "$date": "2026-02-12T09:30:00.000Z"
    },
    "updatedAt": {
      "$date": "2026-02-12T09:30:00.000Z"
    }
  }
]